NEMO_mqtt/__init__.py
NEMO_mqtt/admin.py
NEMO_mqtt/apps.py
NEMO_mqtt/interlocks.py
NEMO_mqtt/models.py
NEMO_mqtt-0.3.5.dist-info/LICENSE
NEMO_mqtt-0.3.5.dist-info/METADATA
NEMO_mqtt-0.3.5.dist-info/WHEEL
NEMO_mqtt-0.3.5.dist-info/top_level.txt
NEMO_mqtt-0.3.5.dist-info/RECORD
