Metadata-Version: 2.1
Name: NEMO-mqtt
Version: 0.3.5
Summary: MQTT plugin for NEMO
Home-page: https://gitlab.com/r-xyz/nemo-mqtt
Author: r-xyz
Maintainer: r-xyz
License: MIT
Keywords: NEMO
Classifier: Development Status :: 3 - Alpha
Classifier: Intended Audience :: Developers
Classifier: License :: OSI Approved :: MIT License
Classifier: Framework :: Django :: 3.2
Classifier: Programming Language :: Python :: 3.9
Classifier: Programming Language :: Python :: 3.10
Classifier: Programming Language :: Python :: 3.11
Requires-Python: >=3.9
License-File: LICENSE
Requires-Dist: django
Requires-Dist: paho-mqtt
Provides-Extra: nemo
Requires-Dist: NEMO >=5.0.0 ; extra == 'nemo'
Provides-Extra: nemo-ce
Requires-Dist: NEMO-CE >=2.0.0 ; extra == 'nemo-ce'
